thea_process_data/__init__.py
thea_process_data/common.py
thea_process_data/thea_process_data.py
thea_process_data-0.0.3.dist-info/LICENSE
thea_process_data-0.0.3.dist-info/METADATA
thea_process_data-0.0.3.dist-info/WHEEL
thea_process_data-0.0.3.dist-info/entry_points.txt
thea_process_data-0.0.3.dist-info/top_level.txt
thea_process_data-0.0.3.dist-info/RECORD
