Metadata-Version: 2.1
Name: thea-process-data
Version: 0.0.3
Summary: A python package demo
Author-email: Thea Zhu <theazhuu@gmail.com>
License: MIT License
Project-URL: Homepage, https://github.com/TheaZhuu/thea-process-data
Keywords: thea-process-data
Classifier: Intended Audience :: Developers
Classifier: License :: OSI Approved :: MIT License
Classifier: Natural Language :: English
Classifier: Programming Language :: Python :: 3.8
Classifier: Programming Language :: Python :: 3.9
Classifier: Programming Language :: Python :: 3.10
Classifier: Programming Language :: Python :: 3.11
Classifier: Programming Language :: Python :: 3.12
Requires-Python: >=3.8
License-File: LICENSE
Requires-Dist: numpy
Requires-Dist: pandas
Provides-Extra: all
Requires-Dist: thea-process-data[extra] ; extra == 'all'
Provides-Extra: extra
Requires-Dist: pandas ; extra == 'extra'
